pygitapi/__init__.py
pygitapi/github.py
pygitapi/utils.py
pygitapi-1.0.0.dist-info/LICENSE
pygitapi-1.0.0.dist-info/METADATA
pygitapi-1.0.0.dist-info/WHEEL
pygitapi-1.0.0.dist-info/top_level.txt
pygitapi-1.0.0.dist-info/RECORD
