Metadata-Version: 2.1
Name: pygitapi
Version: 1.0.0
Summary: "A Python wrapper for the GitHub API"
Home-page: https://github.com/DillonB07/GitAPI
Author: Dillon Barnes
Author-email: dillonbarnes07@gmail.com
License: LGPLv3
Project-URL: Documentation, https://github.com/DillonB07/GitAPI
Project-URL: Source Code, https://github.com/DillonB07/GitAPI
Project-URL: Bug Tracker, https://github.com/DillonB07/GitAPI/issues
Project-URL: Discussions, https://github.com/DillonB07/GitAPI/discussions
Keywords: dillonb07,utils,github,api,graphql
Platform: UNKNOWN
Classifier: Programming Language :: Python :: 3
Classifier: License :: OSI Approved :: GNU Lesser General Public License v3 (LGPLv3)
Classifier: Operating System :: OS Independent
Classifier: Topic :: Utilities
Requires-Python: >=3.6
License-File: LICENSE
Requires-Dist: requests
